LICENSE
README.md
esque_wire/__init__.py
esque_wire/_base_connection.py
esque_wire/connection.py
esque_wire/protocol/__init__.py
esque_wire/protocol/constants.py
esque_wire/protocol/request.py
esque_wire/protocol/serializers/__init__.py
esque_wire/protocol/serializers/api/__init__.py
esque_wire/protocol/serializers/api/_main_serializers.py
esque_wire/protocol/serializers/api/add_offsets_to_txn_request.py
esque_wire/protocol/serializers/api/add_offsets_to_txn_response.py
esque_wire/protocol/serializers/api/add_partitions_to_txn_request.py
esque_wire/protocol/serializers/api/add_partitions_to_txn_response.py
esque_wire/protocol/serializers/api/alter_configs_request.py
esque_wire/protocol/serializers/api/alter_configs_response.py
esque_wire/protocol/serializers/api/alter_replica_log_dirs_request.py
esque_wire/protocol/serializers/api/alter_replica_log_dirs_response.py
esque_wire/protocol/serializers/api/api_versions_request.py
esque_wire/protocol/serializers/api/api_versions_response.py
esque_wire/protocol/serializers/api/controlled_shutdown_request.py
esque_wire/protocol/serializers/api/controlled_shutdown_response.py
esque_wire/protocol/serializers/api/create_acls_request.py
esque_wire/protocol/serializers/api/create_acls_response.py
esque_wire/protocol/serializers/api/create_delegation_token_request.py
esque_wire/protocol/serializers/api/create_delegation_token_response.py
esque_wire/protocol/serializers/api/create_partitions_request.py
esque_wire/protocol/serializers/api/create_partitions_response.py
esque_wire/protocol/serializers/api/create_topics_request.py
esque_wire/protocol/serializers/api/create_topics_response.py
esque_wire/protocol/serializers/api/delete_acls_request.py
esque_wire/protocol/serializers/api/delete_acls_response.py
esque_wire/protocol/serializers/api/delete_groups_request.py
esque_wire/protocol/serializers/api/delete_groups_response.py
esque_wire/protocol/serializers/api/delete_records_request.py
esque_wire-0.1.0.dist-info/LICENSE
esque_wire-0.1.0.dist-info/WHEEL
esque_wire-0.1.0.dist-info/METADATA
esque_wire-0.1.0.dist-info/RECORD
