Metadata-Version: 2.1
Name: esque-wire
Version: 0.1.0
Summary: A complete implementation of the Kafka API
Home-page: https://github.com/real.digital/esque-wire
License: MIT
Keywords: kafka,cli,commandline,administration,operation
Author: real-digital
Author-email: opensource@real-digital.de
Requires-Python: >=3.6,<4.0
Classifier: Development Status :: 3 - Alpha
Classifier: Intended Audience :: Developers
Classifier: License :: OSI Approved :: MIT License
Classifier: Programming Language :: Python :: 3
Classifier: Programming Language :: Python :: 3.6
Classifier: Programming Language :: Python :: 3.7
Classifier: Programming Language :: Python :: 3.8
Classifier: Topic :: Software Development
Classifier: Topic :: Software Development :: Libraries
Classifier: Typing :: Typed
Project-URL: Repository, https://github.com/real.digital/esque-wire
